pyciff-0.2.0.dist-info/METADATA
pyciff-0.2.0.dist-info/WHEEL
pyciff/__init__.py
pyciff/pyciff.cpython-39-x86_64-linux-gnu.so
pyciff-0.2.0.dist-info/RECORD
