Metadata-Version: 2.1
Name: pyciff
Version: 0.2.0
Classifier: License :: OSI Approved :: Apache Software License
Classifier: Development Status :: 3 - Alpha
Classifier: Intended Audience :: Developers
Classifier: Programming Language :: Python
Classifier: Programming Language :: Rust
Classifier: Operating System :: POSIX
Classifier: Operating System :: MacOS :: MacOS X
Author: Michal Siedlaczek <siedlaczek@pm.me>, Joel Mackenzie <joelmmackenzie@gmail.com>
Author-email: Michal Siedlaczek <siedlaczek@pm.me>, Joel Mackenzie <joelmmackenzie@gmail.com>
